pytrax/__RandomWalk__.py
pytrax/__init__.py
pytrax-0.1.2.dist-info/LICENSE
pytrax-0.1.2.dist-info/METADATA
pytrax-0.1.2.dist-info/WHEEL
pytrax-0.1.2.dist-info/top_level.txt
pytrax-0.1.2.dist-info/RECORD
